README.rst
jsonlight.py
setup.py
jsonlight.egg-info/PKG-INFO
jsonlight.egg-info/SOURCES.txt
jsonlight.egg-info/dependency_links.txt
jsonlight.egg-info/requires.txt
jsonlight.egg-info/top_level.txt