Metadata-Version: 2.1
Name: jsonlight
Version: 0.0.2.dev1
Summary: json with rudimentary type encoding/decoding for Python
Home-page: https://yourlabs.io/oss/jsonlight
Author: James Pic
Author-email: jamespic@gmail.com
License: MIT
Keywords: cli
Platform: UNKNOWN
Provides-Extra: test
